aiutil.py
htmlutil.py
jsonutil.py
respondo.py
response.py
text.py
respondo-0.4.0.dist-info/licenses/LICENSE
respondo-0.4.0.dist-info/METADATA
respondo-0.4.0.dist-info/WHEEL
respondo-0.4.0.dist-info/top_level.txt
respondo-0.4.0.dist-info/RECORD
