Metadata-Version: 2.4
Name: respondo
Version: 0.4.0
Summary: Scraping-friendly HTTP, string parsing, JSON helpers, and AI parsing.
Author: Respondo Maintainers
License-Expression: MIT
Keywords: http,scraping,text,json,utilities,llm,ai
Classifier: Programming Language :: Python :: 3
Classifier: Programming Language :: Python :: 3 :: Only
Classifier: Topic :: Internet :: WWW/HTTP
Classifier: Topic :: Text Processing
Requires-Python: >=3.9
License-File: LICENSE
Dynamic: license-file
